{
  "image": ".po-page-content div img",
  "form": {
    "email": ".po-page-content form po-field-container[ng-reflect-label='E-mail'] .po-input",
    "password": ".po-page-content form po-field-container[ng-reflect-label='Senha'] .po-input",
    "passwordMsgErro": ".po-page-content form po-field-container[ng-reflect-label='Senha'] .po-field-container-bottom-text-error",
    "passwordConfirm": ".po-page-content form po-field-container[ng-reflect-label='Confirme a senha'] .po-input",
    "btnSubmit": ".po-page-content form po-button[p-label='Enviar'] .po-button"
  }
}
